package/__init__.py
package/main.py
package/controllers/__init__.py
package/controllers/base.py
package/controllers/releases.py
package/core/__init__.py
package/core/api.py
package/core/exc.py
package/core/releases.py
package/core/version.py
package/ext/__init__.py
package/plugins/__init__.py
package/templates/__init__.py
ttp_scripts-0.2.0a2.dist-info/LICENSE.md
ttp_scripts-0.2.0a2.dist-info/METADATA
ttp_scripts-0.2.0a2.dist-info/WHEEL
ttp_scripts-0.2.0a2.dist-info/entry_points.txt
ttp_scripts-0.2.0a2.dist-info/top_level.txt
ttp_scripts-0.2.0a2.dist-info/RECORD
