Metadata-Version: 2.1
Name: ttp-scripts
Version: 0.2.0a2
Summary: Manage pipeline versions
Home-page: https://github.com/twinthread/ttp-scripts/
Author: Brent Baumgartner
Author-email: brent@twinthread.com
License: unlicensed
Platform: UNKNOWN
Requires-Dist: cement
Requires-Dist: pandas
Requires-Dist: tabulate
Requires-Dist: colorlog
Requires-Dist: requests
Requires-Dist: jinja2
